cfaster/__init__.py
cfaster/__main__.py
cfaster/scrapers/__init__.py
cfaster/scrapers/codeforces.py
cfaster/scrapers/utils/__init__.py
cfaster/scrapers/utils/files.py
cfaster/scrapers/utils/urls.py
cfaster-0.0.2.dist-info/LICENSE
cfaster-0.0.2.dist-info/METADATA
cfaster-0.0.2.dist-info/WHEEL
cfaster-0.0.2.dist-info/entry_points.txt
cfaster-0.0.2.dist-info/top_level.txt
cfaster-0.0.2.dist-info/RECORD
