Metadata-Version: 2.1
Name: cfaster
Version: 0.0.2
Summary: A package to get all you need to start a            programming contest as fast as possible
Home-page: https://github.com/vitorfhc/cfaster
Author: Vitor Falcão Costa
Author-email: vitorfhcosta@gmail.com
License: UNKNOWN
Keywords: contest,scraper,tools,codeforces,uva
Platform: UNKNOWN
Classifier: Programming Language :: Python :: 3
Classifier: License :: OSI Approved :: GNU General Public License v3 (GPLv3)
Classifier: Operating System :: OS Independent
Classifier: Intended Audience :: Developers
Requires-Dist: beautifulsoup4 (==4.7.1)
Requires-Dist: Click (==7.0)
Requires-Dist: requests (==2.22.0)
